fastspell/__init__.py
fastspell/fastspell.py
fastspell/fastspell_download.py
fastspell/util.py
fastspell/config/hunspell.yaml
fastspell/config/similar.yaml
fastspell-0.12.dist-info/LICENSE
fastspell-0.12.dist-info/METADATA
fastspell-0.12.dist-info/WHEEL
fastspell-0.12.dist-info/entry_points.txt
fastspell-0.12.dist-info/top_level.txt
fastspell-0.12.dist-info/RECORD
