Metadata-Version: 2.1
Name: fastspell
Version: 0.12
Summary: Targetted language identifier, based on FastText and Hunspell.
Author-email: Prompsit Language Engineering <info@prompsit.com>
Maintainer-email: Marta Bañon <mbanon@prompsit.com>, Jaume Zaragoza <jzaragoza@prompsit.com>
License: GNU GENERAL PUBLIC LICENSE
Project-URL: Homepage, https://github.com/mbanon/fastspell
Project-URL: FastSpell on GitHub, https://github.com/mbanon/fastspell
Project-URL: Prompsit Language Engineering, http://www.prompsit.com
Project-URL: Paracrawl, https://paracrawl.eu/
Project-URL: MaCoCu, https://macocu.eu
Project-URL: HPLT Project, https://hplt-project.org
Classifier: Environment :: Console
Classifier: Intended Audience :: Science/Research
Classifier: Programming Language :: Python :: 3.8
Classifier: Programming Language :: Python :: 3.9
Classifier: Programming Language :: Python :: 3.10
Classifier: License :: OSI Approved :: GNU General Public License v3 (GPLv3)
Classifier: Operating System :: POSIX :: Linux
Classifier: Topic :: Scientific/Engineering :: Artificial Intelligence
Classifier: Topic :: Text Processing :: Linguistic
Classifier: Topic :: Software Development :: Libraries :: Python Modules
Classifier: Topic :: Text Processing :: Filters
Requires-Python: >=3.8
License-File: LICENSE
Requires-Dist: cyhunspell <=2.0.3,>=2.0.2
Requires-Dist: fastspell-dictionaries ==3.3
Requires-Dist: fasttext-wheel ==0.9.2
Requires-Dist: numpy <2
Requires-Dist: urllib3
Requires-Dist: PyYAML
Requires-Dist: regex
Requires-Dist: hanzidentifier
